winble.cp36-win_amd64.pyd
WinBle-0.0.1.dist-info/METADATA
WinBle-0.0.1.dist-info/WHEEL
WinBle-0.0.1.dist-info/top_level.txt
WinBle-0.0.1.dist-info/RECORD
